pyverif/__init__.py
pyverif/entry.py
pyverif-0.1.2.dist-info/LICENSE
pyverif-0.1.2.dist-info/METADATA
pyverif-0.1.2.dist-info/WHEEL
pyverif-0.1.2.dist-info/top_level.txt
pyverif-0.1.2.dist-info/RECORD
